usage_tracker/__init__.py
usage_tracker/tracker.py
usage_tracker-0.4.0.dist-info/METADATA
usage_tracker-0.4.0.dist-info/WHEEL
usage_tracker-0.4.0.dist-info/RECORD
